bojaxns/__init__.py
bojaxns/base.py
bojaxns/basic.py
bojaxns/common.py
bojaxns/experiment.py
bojaxns/parameter_space.py
bojaxns/service.py
bojaxns/utils.py
bojaxns/gaussian_process_formulation/__init__.py
bojaxns/gaussian_process_formulation/bayesian_optimiser.py
bojaxns/gaussian_process_formulation/distribution_math.py
bojaxns/gaussian_process_formulation/multi_step_lookahead.py
bojaxns/gaussian_process_formulation/tests/__init__.py
bojaxns/gaussian_process_formulation/tests/test_bayesian_optimiser.py
bojaxns/gaussian_process_formulation/tests/test_distribution_maths.py
bojaxns/tests/__init__.py
bojaxns/tests/test_experiment.py
bojaxns/tests/test_parameter_space.py
bojaxns/tests/test_utils.py
bojaxns-1.1.1.dist-info/LICENSE
bojaxns-1.1.1.dist-info/METADATA
bojaxns-1.1.1.dist-info/WHEEL
bojaxns-1.1.1.dist-info/top_level.txt
bojaxns-1.1.1.dist-info/RECORD
