Metadata-Version: 2.1
Name: bojaxns
Version: 1.1.1
Summary: Bayesian Optimisation with JAXNS
Home-page: https://github.com/joshuaalbert/bojaxns
Author: Joshua G. Albert
Author-email: albert@strw.leidenuniv.nl
Classifier: Programming Language :: Python :: 3
Classifier: License :: OSI Approved :: Apache Software License
Classifier: Operating System :: OS Independent
Requires-Python: >=3.9
License-File: LICENSE
Requires-Dist: jax
Requires-Dist: jaxlib
Requires-Dist: tensorflow-probability
Requires-Dist: jaxns ==2.4.4
Requires-Dist: pydantic
Requires-Dist: chex >=0.0.8
Requires-Dist: mctx
Requires-Dist: pyDOE2
Requires-Dist: matplotlib
Requires-Dist: etils
